LICENSE
MANIFEST.in
README
setup.cfg
setup.py
fabric/__init__.py
fabric/contrib/__init__.py
fabric/contrib/xfiles/__init__.py
fabric/contrib/xfiles/reader.py
fabric_contrib.xfiles.egg-info/PKG-INFO
fabric_contrib.xfiles.egg-info/SOURCES.txt
fabric_contrib.xfiles.egg-info/dependency_links.txt
fabric_contrib.xfiles.egg-info/entry_points.txt
fabric_contrib.xfiles.egg-info/namespace_packages.txt
fabric_contrib.xfiles.egg-info/not-zip-safe
fabric_contrib.xfiles.egg-info/requires.txt
fabric_contrib.xfiles.egg-info/top_level.txt
test/test_xfiles.py