Metadata-Version: 1.0
Name: fabric-contrib.xfiles
Version: 0.1.1
Summary: Fabric extension: xfiles
Home-page: http://bitbucket.org/jmu/fabric-contrib
Author: Juha Mustonen
Author-email: juha.p.mustonen@gmail.com
License: MIT
Download-URL: http://pypi.python.org/pypi/xfiles
Platform: any
Classifier: Development Status :: 4 - Beta
Classifier: Environment :: Console
Classifier: Environment :: Web Environment
Classifier: Intended Audience :: Developers
Classifier: License :: OSI Approved :: MIT License
Classifier: Operating System :: OS Independent
Classifier: Programming Language :: Python
Classifier: Topic :: Utilities
